tmlogsearch/__init__.py
tmlogsearch/app.py
tmlogsearch/templates/index.html
TmLogSearch-1.0.0.dist-info/METADATA
TmLogSearch-1.0.0.dist-info/WHEEL
TmLogSearch-1.0.0.dist-info/entry_points.txt
TmLogSearch-1.0.0.dist-info/top_level.txt
TmLogSearch-1.0.0.dist-info/RECORD
