Metadata-Version: 2.1
Name: TmLogSearch
Version: 1.0.0
Requires-Dist: Flask
Requires-Dist: paramiko
Requires-Dist: flask-cors
